pyvirtualcam/__init__.py
pyvirtualcam/_native_macos_obs_cmioextension.cpython-313-darwin.so
pyvirtualcam/_native_macos_obs_dal.cpython-313-darwin.so
pyvirtualcam/_version.py
pyvirtualcam/camera.py
pyvirtualcam/util.py
pyvirtualcam-0.15.0.dist-info/licenses/LICENSE
pyvirtualcam-0.15.0.dist-info/METADATA
pyvirtualcam-0.15.0.dist-info/WHEEL
pyvirtualcam-0.15.0.dist-info/top_level.txt
pyvirtualcam-0.15.0.dist-info/RECORD
